decorapy/__init__.py
decorapy/benchmark.py
decorapy/circuit_breaker.py
decorapy/log_calls.py
decorapy/lru_memoize.py
decorapy/memoization.py
decorapy/retry.py
decorapy/singleton.py
decorapy/throttle.py
decorapy/timing.py
decorapy/trace.py
decorapy/validation.py
decorapy-0.1.0.dist-info/METADATA
decorapy-0.1.0.dist-info/WHEEL
decorapy-0.1.0.dist-info/RECORD
