Metadata-Version: 2.4
Name: decorapy
Version: 0.1.0
Summary: DecoraPy - A Collection of Powerful Python Decorators
Project-URL: homepage, https://github.com/Mathews-Tom/decorapy
Project-URL: repository, https://github.com/Mathews-Tom/decorapy
Requires-Python: >=3.12
Requires-Dist: twine>=6.1.0
